cpfem/EulerAngle.py
cpfem/Grain.py
cpfem/__init__.py
cpfem/cpfemConstants.py
cpfem/example.py
cpfem/material_io.py
cpfem/Material/Material.py
cpfem/Material/MaterialBase.py
cpfem/Material/MaterialModel.py
cpfem/Material/MaterialOdb.py
cpfem/Material/Ratios.py
cpfem/Material/Regularization.py
cpfem/Material/__init__.py
cpfem/Material/evaluateMaterial.py
cpfem/Material/Others/__init__.py
cpfem/Material/Others/User/Depvar.py
cpfem/Material/Others/User/UserDefinedField.py
cpfem/Material/Others/User/UserMaterial.py
cpfem/Material/Others/User/UserOutputVariables.py
cpfem/Material/Others/User/__init__.py
cpfem/neper2cae/__init__.py
cpfem/neper2cae/neper.py
cpfem/neper2cae/neper2cae.py
cpfem/neper2cae/neperparser.py
cpfem-0.0.2.dist-info/LICENSE
cpfem-0.0.2.dist-info/METADATA
cpfem-0.0.2.dist-info/WHEEL
cpfem-0.0.2.dist-info/top_level.txt
cpfem-0.0.2.dist-info/RECORD
