Metadata-Version: 2.1
Name: cpfem
Version: 0.0.2
Summary: Tools for CPFEM
Home-page: https://github.com/pypa/sampleproject
Author: Jingyu Sun
Author-email: sun.jingyu@outlook.com
License: UNKNOWN
Project-URL: Bug Tracker, https://github.com/pypa/sampleproject/issues
Platform: UNKNOWN
Classifier: Programming Language :: Python :: 3
Classifier: License :: OSI Approved :: MIT License
Classifier: Operating System :: OS Independent
Requires-Python: >=3.6
License-File: LICENSE
